gpolyencode.py
setup.py
GPolyEncode.egg-info/PKG-INFO
GPolyEncode.egg-info/SOURCES.txt
GPolyEncode.egg-info/dependency_links.txt
GPolyEncode.egg-info/top_level.txt