Metadata-Version: 1.1
Name: GPolyEncode
Version: 0.1.0
Summary: Google Maps Polyline encoding (pure Python)
Home-page: http://code.google.com/p/py-gpolyencode/
Author: Robert Coup
Author-email: robert.coup@koordinates.com
License: UNKNOWN
Keywords: gis,geospatial,google-maps,gmaps,mapping
Platform: UNKNOWN
Classifier: Development Status :: 4 - Beta
Classifier: Environment :: Web Environment
Classifier: License :: OSI Approved :: BSD License
Classifier: Intended Audience :: Developers
Classifier: Operating System :: OS Independent
Classifier: Programming Language :: Python
Classifier: Topic :: Scientific/Engineering :: GIS
Classifier: Topic :: Utilities
Provides: gpolyencode
